YW_matchups/AC_acolite.py
YW_matchups/AC_l2gen.py
YW_matchups/AC_polymer.py
YW_matchups/__init__.py
YW_matchups/polymer_matchups.py
YW_matchups/run.py
YW_matchups-2.1.3.dist-info/METADATA
YW_matchups-2.1.3.dist-info/WHEEL
YW_matchups-2.1.3.dist-info/top_level.txt
YW_matchups-2.1.3.dist-info/RECORD
