Metadata-Version: 2.1
Name: YW-matchups
Version: 2.1.3
Summary: Find satellite matchups for aquatic remote sensing
Author: Yulun Wu
Author-email: yulunwu8@gmail.com
Classifier: Programming Language :: Python :: 3
Requires-Python: >=3.8
Requires-Dist: pyproj
Requires-Dist: pandas
Requires-Dist: numpy
Requires-Dist: netCDF4
